<?xml version="1.0" encoding="UTF-8"?>
<con:soapui-project id="49656ff8-1b9c-4201-9ae1-a5ad33b443ee" created="3.53.0" activeEnvironment="Default environment" encryptionMode="Not encrypted" name="Project 1" projectVersion="" updated="3.53.0 2024-05-13T12:06:25Z" xmlns:con="http://eviware.com/soapui/config">
  <con:settings/>
  <con:interface xsi:type="con:WsdlInterface" id="b0c9b4c9-82a4-44ac-9338-12bce62b4918" wsaVersion="NONE" name="CalculatorSoap" type="wsdl" bindingName="{http://tempuri.org/}CalculatorSoap" soapVersion="1_1" anonymous="optional" definition="http://www.dneonline.com/calculator.asmx?wsdl" xmlns:xsi="http://www.w3.org/2001/XMLSchema-instance">
    <con:settings id="91064b24-04f0-47ff-ac9a-55271d1b7dd2"/>
    <con:definitionCache/>
    <con:endpoints>
      <con:endpoint>http://www.dneonline.com/calculator.asmx</con:endpoint>
    </con:endpoints>
    <con:operation id="dae1b0f2-6c89-4dbb-8ef7-19488c92bd4d" isOneWay="false" action="http://tempuri.org/Add" name="Add" bindingOperationName="Add" type="Request-Response" inputName="" receivesAttachments="false" sendsAttachments="false" anonymous="optional">
      <con:settings/>
      <con:call id="3632fd51-d430-4efa-bcbc-016035510d62" name="Add Request">
        <con:settings/>
        <con:encoding>UTF-8</con:encoding>
        <con:endpoint>http://www.dneonline.com/calculator.asmx</con:endpoint>
        <con:request><![CDATA[<soapenv:Envelope xmlns:soapenv="http://schemas.xmlsoap.org/soap/envelope/" xmlns:tem="http://tempuri.org/">\r
   <soapenv:Header/>\r
   <soapenv:Body>\r
      <tem:Add>\r
         <tem:intA>?</tem:intA>\r
         <tem:intB>?</tem:intB>\r
      </tem:Add>\r
   </soapenv:Body>\r
</soapenv:Envelope>]]></con:request>
        <con:credentials>
          <con:selectedAuthProfile>No Authorization</con:selectedAuthProfile>
          <con:authType>No Authorization</con:authType>
        </con:credentials>
        <con:wsaConfig mustUnderstand="NONE" version="200508" action="http://tempuri.org/Add"/>
      </con:call>
    </con:operation>
    <con:operation id="9f315723-bb79-45ee-a5bd-1d4cf8b7327a" isOneWay="false" action="http://tempuri.org/Divide" name="Divide" bindingOperationName="Divide" type="Request-Response" inputName="" receivesAttachments="false" sendsAttachments="false" anonymous="optional">
      <con:settings/>
      <con:call id="fbcd4c4b-45b7-47c4-ba31-3f61f93e5410" name="Divide Request">
        <con:settings/>
        <con:encoding>UTF-8</con:encoding>
        <con:endpoint>http://www.dneonline.com/calculator.asmx</con:endpoint>
        <con:request><![CDATA[<soapenv:Envelope xmlns:soapenv="http://schemas.xmlsoap.org/soap/envelope/" xmlns:tem="http://tempuri.org/">\r
   <soapenv:Header/>\r
   <soapenv:Body>\r
      <tem:Divide>\r
         <tem:intA>?</tem:intA>\r
         <tem:intB>?</tem:intB>\r
      </tem:Divide>\r
   </soapenv:Body>\r
</soapenv:Envelope>]]></con:request>
        <con:credentials>
          <con:selectedAuthProfile>No Authorization</con:selectedAuthProfile>
          <con:authType>No Authorization</con:authType>
        </con:credentials>
        <con:wsaConfig mustUnderstand="NONE" version="200508" action="http://tempuri.org/Divide"/>
      </con:call>
    </con:operation>
    <con:operation id="f6599347-0731-444f-be8c-07c890b019ad" isOneWay="false" action="http://tempuri.org/Multiply" name="Multiply" bindingOperationName="Multiply" type="Request-Response" inputName="" receivesAttachments="false" sendsAttachments="false" anonymous="optional">
      <con:settings/>
      <con:call id="e6f8dabb-3ea6-4e2d-ac3c-05ce9b472ed5" name="Multiply Request">
        <con:settings/>
        <con:encoding>UTF-8</con:encoding>
        <con:endpoint>http://www.dneonline.com/calculator.asmx</con:endpoint>
        <con:request><![CDATA[<soapenv:Envelope xmlns:soapenv="http://schemas.xmlsoap.org/soap/envelope/" xmlns:tem="http://tempuri.org/">\r
   <soapenv:Header/>\r
   <soapenv:Body>\r
      <tem:Multiply>\r
         <tem:intA>?</tem:intA>\r
         <tem:intB>?</tem:intB>\r
      </tem:Multiply>\r
   </soapenv:Body>\r
</soapenv:Envelope>]]></con:request>
        <con:credentials>
          <con:selectedAuthProfile>No Authorization</con:selectedAuthProfile>
          <con:authType>No Authorization</con:authType>
        </con:credentials>
        <con:wsaConfig mustUnderstand="NONE" version="200508" action="http://tempuri.org/Multiply"/>
      </con:call>
    </con:operation>
    <con:operation id="83c5f3c4-bae1-4e3d-b197-4409a485cd8c" isOneWay="false" action="http://tempuri.org/Subtract" name="Subtract" bindingOperationName="Subtract" type="Request-Response" inputName="" receivesAttachments="false" sendsAttachments="false" anonymous="optional">
      <con:settings/>
      <con:call id="7e053901-ff31-4dc1-b60c-b2accf02d443" name="Subtract Request">
        <con:settings/>
        <con:encoding>UTF-8</con:encoding>
        <con:endpoint>http://www.dneonline.com/calculator.asmx</con:endpoint>
        <con:request><![CDATA[<soapenv:Envelope xmlns:soapenv="http://schemas.xmlsoap.org/soap/envelope/" xmlns:tem="http://tempuri.org/">\r
   <soapenv:Header/>\r
   <soapenv:Body>\r
      <tem:Subtract>\r
         <tem:intA>?</tem:intA>\r
         <tem:intB>?</tem:intB>\r
      </tem:Subtract>\r
   </soapenv:Body>\r
</soapenv:Envelope>]]></con:request>
        <con:credentials>
          <con:selectedAuthProfile>No Authorization</con:selectedAuthProfile>
          <con:authType>No Authorization</con:authType>
        </con:credentials>
        <con:wsaConfig mustUnderstand="NONE" version="200508" action="http://tempuri.org/Subtract"/>
      </con:call>
    </con:operation>
  </con:interface>
  <con:testSuite id="5038436d-78c5-4233-a75b-f53036dad0df" name="Project 1 Test Suite 1">
    <con:settings id="94152051-b2c5-4f90-91f1-b011388adf95"/>
    <con:runType>SEQUENTIAL</con:runType>
    <con:testCase id="a70fc06c-41d3-41a7-945c-d9b50480aa8a" discardOkResults="false" failOnError="false" failTestCaseOnErrors="true" keepSession="false" name="Project 1 Test Case 1" searchProperties="true" timeout="0">
      <con:settings/>
      <con:testStep type="request" id="7dde00eb-4e97-4725-aa19-977b03bc2378" name="CalculatorSoap Add-Add Request">
        <con:settings/>
        <con:config xsi:type="con:RequestStep" xmlns:xsi="http://www.w3.org/2001/XMLSchema-instance">
          <con:interface>CalculatorSoap</con:interface>
          <con:operation>Add</con:operation>
          <con:request name="CalculatorSoap Add-Add Request" outgoingWss="" incomingWss="" timeout="" sslKeystore="" useWsAddressing="false" useWsReliableMessaging="false" wssPasswordType="" id="189808bb-fb01-4d60-a926-dfdeed477a94">
            <con:settings>
              <con:setting id="com.eviware.soapui.impl.wsdl.WsdlRequest@request-headers">&lt;xml-fragment/></con:setting>
            </con:settings>
            <con:encoding>UTF-8</con:encoding>
            <con:endpoint>http://www.dneonline.com/calculator.asmx</con:endpoint>
            <con:request><![CDATA[<?xml version="1.0" encoding="UTF-8"?>\r
<soapenv:Envelope xmlns:soapenv="http://schemas.xmlsoap.org/soap/envelope/" xmlns:tem="http://tempuri.org/">\r
   <soapenv:Header />\r
   <soapenv:Body>\r
      <tem:Add>\r
         <tem:intA>12</tem:intA>\r
         <tem:intB>15</tem:intB>\r
      </tem:Add>\r
   </soapenv:Body>\r
</soapenv:Envelope>\r]]></con:request>
            <con:assertion type="SOAP Response" id="99b53975-40a9-4865-bd3a-d8fe143748e1" name="SOAP Response"/>
            <con:assertion type="Valid HTTP Status Codes" id="e541a4df-bba1-4938-80ff-3a615b28b9b7" name="Valid HTTP Status Codes">
              <con:settings/>
              <con:configuration>
                <codes>200</codes>
              </con:configuration>
            </con:assertion>
            <con:assertion type="Schema Compliance" id="bd877655-d376-4c27-84b7-b6e08070f86d" name="Schema Compliance">
              <con:configuration/>
            </con:assertion>
            <con:assertion type="SOAP Fault Assertion" id="b045f213-f063-41c2-82fd-7866e841d1e7" name="Not SOAP Fault"/>
            <con:credentials>
              <con:selectedAuthProfile>No Authorization</con:selectedAuthProfile>
              <con:authType>No Authorization</con:authType>
            </con:credentials>
            <con:jmsConfig JMSDeliveryMode="PERSISTENT"/>
            <con:wsaConfig mustUnderstand="NONE" version="200508" action="http://tempuri.org/Add"/>
            <con:wsrmConfig version="1.2"/>
          </con:request>
        </con:config>
      </con:testStep>
      <con:testStep type="request" id="8df62fde-eddb-4a53-ad5e-2d12c77b06fd" name="CalculatorSoap Divide-Divide Request">
        <con:settings/>
        <con:config xsi:type="con:RequestStep" xmlns:xsi="http://www.w3.org/2001/XMLSchema-instance">
          <con:interface>CalculatorSoap</con:interface>
          <con:operation>Divide</con:operation>
          <con:request name="CalculatorSoap Divide-Divide Request" outgoingWss="" incomingWss="" timeout="" sslKeystore="" useWsAddressing="false" useWsReliableMessaging="false" wssPasswordType="" id="b962a10a-8a3f-4f2d-bba4-8074f2efacec">
            <con:settings/>
            <con:encoding>UTF-8</con:encoding>
            <con:endpoint>http://www.dneonline.com/calculator.asmx</con:endpoint>
            <con:request><![CDATA[<soapenv:Envelope xmlns:soapenv="http://schemas.xmlsoap.org/soap/envelope/" xmlns:tem="http://tempuri.org/">\r
   <soapenv:Header/>\r
   <soapenv:Body>\r
      <tem:Divide>\r
         <tem:intA>?</tem:intA>\r
         <tem:intB>?</tem:intB>\r
      </tem:Divide>\r
   </soapenv:Body>\r
</soapenv:Envelope>]]></con:request>
            <con:assertion type="SOAP Response" id="5d31a4d5-8890-4ff8-b448-c4789abf4330" name="SOAP Response"/>
            <con:assertion type="Valid HTTP Status Codes" id="5f3df75f-b2bb-480e-8fae-494a85a479fa" name="Valid HTTP Status Codes">
              <con:settings/>
              <con:configuration>
                <codes>200</codes>
              </con:configuration>
            </con:assertion>
            <con:assertion type="Schema Compliance" id="320c1e03-b534-44d7-84c7-0ee4b65a41a6" name="Schema Compliance">
              <con:configuration/>
            </con:assertion>
            <con:assertion type="SOAP Fault Assertion" id="605a8f01-4d0a-4bc0-9676-4b93b9d8205b" name="Not SOAP Fault"/>
            <con:credentials>
              <con:selectedAuthProfile>No Authorization</con:selectedAuthProfile>
              <con:authType>No Authorization</con:authType>
            </con:credentials>
            <con:wsaConfig mustUnderstand="NONE" version="200508" action="http://tempuri.org/Divide"/>
          </con:request>
        </con:config>
      </con:testStep>
      <con:testStep type="request" id="54d98e16-3edf-4f55-bb9a-57a4def3b8c1" name="CalculatorSoap Multiply-Multiply Request">
        <con:settings/>
        <con:config xsi:type="con:RequestStep" xmlns:xsi="http://www.w3.org/2001/XMLSchema-instance">
          <con:interface>CalculatorSoap</con:interface>
          <con:operation>Multiply</con:operation>
          <con:request name="CalculatorSoap Multiply-Multiply Request" outgoingWss="" incomingWss="" timeout="" sslKeystore="" useWsAddressing="false" useWsReliableMessaging="false" wssPasswordType="" id="6b29153a-8c85-4d96-8f07-de60c7b67a0a">
            <con:settings/>
            <con:encoding>UTF-8</con:encoding>
            <con:endpoint>http://www.dneonline.com/calculator.asmx</con:endpoint>
            <con:request><![CDATA[<soapenv:Envelope xmlns:soapenv="http://schemas.xmlsoap.org/soap/envelope/" xmlns:tem="http://tempuri.org/">\r
   <soapenv:Header/>\r
   <soapenv:Body>\r
      <tem:Multiply>\r
         <tem:intA>?</tem:intA>\r
         <tem:intB>?</tem:intB>\r
      </tem:Multiply>\r
   </soapenv:Body>\r
</soapenv:Envelope>]]></con:request>
            <con:assertion type="SOAP Response" id="54237cfb-a915-42f1-b59e-09b136304a61" name="SOAP Response"/>
            <con:assertion type="Valid HTTP Status Codes" id="d50817ee-a20b-455f-a179-8421053aa9e2" name="Valid HTTP Status Codes">
              <con:settings/>
              <con:configuration>
                <codes>200</codes>
              </con:configuration>
            </con:assertion>
            <con:assertion type="Schema Compliance" id="5c128fa4-4de4-41e8-9add-f7cdc4deb81e" name="Schema Compliance">
              <con:configuration/>
            </con:assertion>
            <con:assertion type="SOAP Fault Assertion" id="fde6bde5-5ea1-4fa0-b21b-e898f38df930" name="Not SOAP Fault"/>
            <con:credentials>
              <con:selectedAuthProfile>No Authorization</con:selectedAuthProfile>
              <con:authType>No Authorization</con:authType>
            </con:credentials>
            <con:wsaConfig mustUnderstand="NONE" version="200508" action="http://tempuri.org/Multiply"/>
          </con:request>
        </con:config>
      </con:testStep>
      <con:testStep type="request" id="0faff8d5-61fc-4e14-9ad9-eeb3aaa5eb0f" name="CalculatorSoap Subtract-Subtract Request">
        <con:settings/>
        <con:config xsi:type="con:RequestStep" xmlns:xsi="http://www.w3.org/2001/XMLSchema-instance">
          <con:interface>CalculatorSoap</con:interface>
          <con:operation>Subtract</con:operation>
          <con:request name="CalculatorSoap Subtract-Subtract Request" outgoingWss="" incomingWss="" timeout="" sslKeystore="" useWsAddressing="false" useWsReliableMessaging="false" wssPasswordType="" id="640a7e4d-e3c6-4e55-81c4-83de0913cbf3">
            <con:settings/>
            <con:encoding>UTF-8</con:encoding>
            <con:endpoint>http://www.dneonline.com/calculator.asmx</con:endpoint>
            <con:request><![CDATA[<soapenv:Envelope xmlns:soapenv="http://schemas.xmlsoap.org/soap/envelope/" xmlns:tem="http://tempuri.org/">\r
   <soapenv:Header/>\r
   <soapenv:Body>\r
      <tem:Subtract>\r
         <tem:intA>?</tem:intA>\r
         <tem:intB>?</tem:intB>\r
      </tem:Subtract>\r
   </soapenv:Body>\r
</soapenv:Envelope>]]></con:request>
            <con:assertion type="SOAP Response" id="345a149e-cbc0-4215-8706-2f7db1ca02b7" name="SOAP Response"/>
            <con:assertion type="Valid HTTP Status Codes" id="1ba197fb-8c2a-4f66-90dd-6c87acf052b7" name="Valid HTTP Status Codes">
              <con:settings/>
              <con:configuration>
                <codes>200</codes>
              </con:configuration>
            </con:assertion>
            <con:assertion type="Schema Compliance" id="2d59f5df-c061-4a14-ab20-cc53e07ca195" name="Schema Compliance">
              <con:configuration/>
            </con:assertion>
            <con:assertion type="SOAP Fault Assertion" id="cf2f7d85-26c1-42cc-9415-ecbefbded650" name="Not SOAP Fault"/>
            <con:credentials>
              <con:selectedAuthProfile>No Authorization</con:selectedAuthProfile>
              <con:authType>No Authorization</con:authType>
            </con:credentials>
            <con:wsaConfig mustUnderstand="NONE" version="200508" action="http://tempuri.org/Subtract"/>
          </con:request>
        </con:config>
      </con:testStep>
      <con:properties/>
      <con:reportParameters/>
    </con:testCase>
    <con:properties/>
    <con:reportParameters/>
  </con:testSuite>
  <con:properties/>
  <con:wssContainer/>
  <con:databaseConnectionContainer/>
  <con:jmsConnectionContainer/>
  <con:oAuth2ProfileContainer/>
  <con:oAuth1ProfileContainer/>
  <con:reporting>
    <con:xmlTemplates/>
    <con:parameters/>
  </con:reporting>
  <con:eventHandlers type="RequestFilter.filterRequest" name="RequestFilter.filterRequest">
    <con:script>// Sample event script to add custom HTTP header to all outgoing REST, SOAP and HTTP(S) calls
// This code is often used for adding custom authentication to ReadyAPI functional tests

// If hardcoding the token, uncomment and change line 5
// token = '4567'

// If your token is parameterized in Project level custom property, uncomment line 8
// token = request.parent.testCase.testSuite.project.getProperty('auth_token').getValue()

// To modify all outgoing calls, remove comments from lines 11 to 16
// headers = request.requestHeaders
// if (headers.containsKey('auth_token2') == false) {
//   headers.put('auth_token2', token)
//   request.requestHeaders = headers
// }</con:script>
  </con:eventHandlers>
  <con:eventHandlers type="TestRunListener.afterStep" name="TestRunListener.afterStep">
    <con:script>// Save all test step results into files
// Change the directory path in line 5 to a location where you want to store details
// then uncomment lines 5 to 10

// filePath = 'C:\\tempOutputDirectory\\'
// fos = new java.io.FileOutputStream(filePath + testStepResult.testStep.label + '.txt', true)
// pw = new java.io.PrintWriter(fos)
// testStepResult.writeTo(pw)
// pw.close()
// fos.close()</con:script>
  </con:eventHandlers>
  <con:authRepository/>
  <con:tags/>
</con:soapui-project>
